point_in_geojson-0.0.10.dist-info/METADATA
point_in_geojson-0.0.10.dist-info/WHEEL
point_in_geojson-0.0.10.dist-info/licenses/LICENSE
point_in_geojson.libs/libgcc_s-b5472b99.so.1
point_in_geojson/__init__.py
point_in_geojson/point_in_geojson.pypy39-pp73-x86-linux-gnu.so
point_in_geojson-0.0.10.dist-info/RECORD
