Metadata-Version: 2.4
Name: point_in_geojson
Version: 0.0.10
Classifier: Programming Language :: Rust
Classifier: Programming Language :: Python :: Implementation :: CPython
Classifier: Programming Language :: Python :: Implementation :: PyPy
Classifier: License :: OSI Approved :: MIT License
License-File: LICENSE
Summary: Checks how a point is related to a GeoJSON shape.
Keywords: geojson,rust,python
Author: Jannis Lübbe <jannisluebbe1982@gmail.com>
Author-email: Jannis Lübbe <jannisluebbe1982@gmail.com>
License: MIT
Requires-Python: >=3.8
Project-URL: Homepage, https://github.com/jaluebbe/point_in_geojson
Project-URL: Issues, https://github.com/jaluebbe/point_in_geojson/issues
